dips/__init__.py
dips/dips.py
dips-0.2.0.data/scripts/dips
dips-0.2.0.dist-info/LICENSE
dips-0.2.0.dist-info/METADATA
dips-0.2.0.dist-info/WHEEL
dips-0.2.0.dist-info/top_level.txt
dips-0.2.0.dist-info/RECORD
