Metadata-Version: 2.1
Name: dips
Version: 0.2.0
Summary: dips: detrending periodic signals
Home-page: https://github.com/aprsa/dips
Author: Andrej Prsa
Author-email: aprsa@villanova.edu
License: UNKNOWN
Platform: UNKNOWN
Classifier: Development Status :: 5 - Production/Stable
Classifier: Programming Language :: Python :: 3
Classifier: Environment :: Console
Classifier: Environment :: X11 Applications
Classifier: Intended Audience :: Science/Research
Classifier: License :: OSI Approved :: GNU General Public License v3 (GPLv3)
Classifier: Operating System :: OS Independent
Classifier: Natural Language :: English
Classifier: Topic :: Scientific/Engineering :: Astronomy
Classifier: Topic :: Scientific/Engineering :: Information Analysis
Classifier: Topic :: Scientific/Engineering :: Mathematics
Requires-Dist: numpy
Requires-Dist: scipy (>=0.13.0)
